sigma/backends/panther/__init__.py
sigma/backends/panther/panther_sdyaml_backend.py
sigma/pipelines/panther/__init__.py
sigma/pipelines/panther/carbon_black_panther_pipeline.py
sigma/pipelines/panther/crowdstrike_panther_pipeline.py
sigma/pipelines/panther/panther_sdyaml_pipeline.py
sigma/pipelines/panther/processing.py
sigma/pipelines/panther/replace_condition_ends_with.py
sigma/pipelines/panther/sdyaml_transformation.py
pysigma_backend_panther_sdyaml-0.2.1.dist-info/LICENSE
pysigma_backend_panther_sdyaml-0.2.1.dist-info/METADATA
pysigma_backend_panther_sdyaml-0.2.1.dist-info/WHEEL
pysigma_backend_panther_sdyaml-0.2.1.dist-info/RECORD
