Metadata-Version: 2.1
Name: pySigma-backend-panther-sdyaml
Version: 0.2.1
Summary: pySigma backend for Panther
Home-page: https://github.com/panther-labs/pySigma-backend-panther-sdyaml
License: LGPL-3.0-only
Author: Josh Esbrook
Author-email: jehockey@umich.edu
Maintainer: Panther Labs Inc
Maintainer-email: pypi@runpanther.io
Requires-Python: >=3.8,<4.0
Classifier: License :: OSI Approved :: GNU Lesser General Public License v3 (LGPLv3)
Classifier: Programming Language :: Python :: 3
Classifier: Programming Language :: Python :: 3.8
Classifier: Programming Language :: Python :: 3.9
Classifier: Programming Language :: Python :: 3.10
Classifier: Programming Language :: Python :: 3.11
Classifier: Programming Language :: Python :: 3.12
Requires-Dist: pysigma (>=0.11,<0.12)
Requires-Dist: pysigma-pipeline-crowdstrike (>=1.0.3,<2.0.0)
Project-URL: Repository, https://github.com/panther-labs/pySigma-backend-panther-sdyaml
